README.rst
setup.py
jira_cycle_extract/__init__.py
jira_cycle_extract/cli.py
jira_cycle_extract/config.py
jira_cycle_extract/cycletime.py
jira_cycle_extract/query.py
jira_cycle_extract.egg-info/PKG-INFO
jira_cycle_extract.egg-info/SOURCES.txt
jira_cycle_extract.egg-info/dependency_links.txt
jira_cycle_extract.egg-info/entry_points.txt
jira_cycle_extract.egg-info/requires.txt
jira_cycle_extract.egg-info/top_level.txt