Metadata-Version: 1.0
Name: jira-cycle-extract
Version: 0.7
Summary: Extract cycle time analytics data from JIRA
Home-page: https://github.com/optilude/jira-cycle-extract
Author: Martin Aspeli
Author-email: optilude@gmail.com
License: MIT
Keywords: agile jira analytics
Platform: UNKNOWN
